{"term":{"term":"exercise","lang":"en"},"level":{"level":2,"page":3},"audio":"\/audio\/en\/uk\/general\/en031571.mp3","type":"word","meanings":[{"term":{"term":"ejercicio","lang":"es"},"deep":1},{"term":{"term":"ejercicios","lang":"es"},"deep":2},{"term":{"term":"ejercicio de","lang":"es"},"deep":3},{"term":{"term":"uso","lang":"es"},"deep":4},{"term":{"term":"maniobras","lang":"es"},"deep":5},{"term":{"term":"hacer ejercicio, ejercitarse","lang":"es"},"deep":6},{"term":{"term":"ejercer","lang":"es"},"deep":7}]}