{"term":{"term":"haw","lang":"en"},"level":{"level":13,"page":6},"audio":"\/audio\/en\/uk\/general\/en1040708.mp3","type":"word","meanings":[{"term":{"term":"vacilar, trabarse la lengua, tartamudear","lang":"es"},"deep":1},{"term":{"term":"baya del espino","lang":"es"},"deep":2},{"term":{"term":"espino","lang":"es"},"deep":3},{"term":{"term":"tercer p\u00e1rpado, membrana nictitante","lang":"es"},"deep":4},{"term":{"term":"a la izquierda","lang":"es"},"deep":5},{"term":{"term":"ir a la izquierda, virar a la izquierda, girar a la izquierda, doblar a la izquierda","lang":"es"},"deep":6}]}