{"term":{"term":"date","lang":"en"},"level":{"level":1,"page":62},"audio":"\/audio\/en\/uk\/general\/en022481.mp3","type":"word","meanings":[{"term":{"term":"fecha","lang":"es"},"deep":1},{"term":{"term":"fecha, a\u00f1o","lang":"es"},"deep":2},{"term":{"term":"cita","lang":"es"},"deep":3},{"term":{"term":"\u00e9poca, per\u00edodo, periodo","lang":"es"},"deep":4},{"term":{"term":"d\u00e1til","lang":"es"},"deep":5},{"term":{"term":"fechar","lang":"es"},"deep":6},{"term":{"term":"datar","lang":"es"},"deep":7},{"term":{"term":"salir con","lang":"es"},"deep":8},{"term":{"term":"delatar la edad de, dar cuenta de la edad de","lang":"es"},"deep":9}]}