{"term":{"term":"harm","lang":"en"},"level":{"level":2,"page":15},"audio":"\/audio\/en\/uk\/general\/en041751.mp3","type":"word","meanings":[{"term":{"term":"lastimar, hacer da\u00f1o","lang":"es"},"deep":1},{"term":{"term":"da\u00f1ar, afectar, causar da\u00f1os, perjudicar","lang":"es"},"deep":2},{"term":{"term":"arruinar, echar a perder, perjudicar","lang":"es"},"deep":3},{"term":{"term":"da\u00f1o, herida","lang":"es"},"deep":4},{"term":{"term":"da\u00f1o, herida, perjuicio","lang":"es"},"deep":5},{"term":{"term":"da\u00f1o, perjuicio","lang":"es"},"deep":6}]}