{"term":{"term":"suck","lang":"en"},"level":{"level":2,"page":80},"audio":"\/audio\/en\/uk\/general\/en085915.mp3","type":"word","meanings":[{"term":{"term":"sorber","lang":"es"},"deep":1},{"term":{"term":"absorber, aspirar, tragarse","lang":"es"},"deep":2},{"term":{"term":"chupar","lang":"es"},"deep":3},{"term":{"term":"succionar","lang":"es"},"deep":4},{"term":{"term":"apestar, ser malo, ser mal\u00edsimo","lang":"es"},"deep":5},{"term":{"term":"meter a alguien en algo","lang":"es"},"deep":6}]}