{"term":{"term":"lodge","lang":"en"},"level":{"level":3,"page":13},"audio":"\/audio\/en\/uk\/general\/en051994.mp3","type":"word","meanings":[{"term":{"term":"atascarse, alojarse","lang":"es"},"deep":1},{"term":{"term":"alojarse, hospedarse","lang":"es"},"deep":2},{"term":{"term":"alojar, hospedar","lang":"es"},"deep":3},{"term":{"term":"clavar, incrustar, meter","lang":"es"},"deep":4},{"term":{"term":"caba\u00f1a","lang":"es"},"deep":5},{"term":{"term":"alojamiento, hotel","lang":"es"},"deep":6},{"term":{"term":"recepci\u00f3n, conserjer\u00eda","lang":"es"},"deep":7},{"term":{"term":"dique","lang":"es"},"deep":8}]}